sarif_manager/__init__.py
sarif_manager/version.py
sarif_manager/bin/__init__.py
sarif_manager/bin/cli.py
sarif_manager/bin/logger.py
sarif_manager/command/__init__.py
sarif_manager/command/azure.py
sarif_manager/command/pdf.py
sarif_manager/command/slack.py
sarif_manager/sarif/__init__.py
sarif_manager/sarif/azure_sarif.py
sarif_manager/sarif/azure_sarif_finding.py
sarif_manager/sarif/azure_sarif_utils.py
sarif_manager/sarif/pdf_finding_details.py
sarif_manager/sarif/pdf_findings.py
sarif_manager/sarif/pdf_letterhead.py
sarif_manager/sarif/pdf_sarif.py
sarif_manager/sarif/pdf_settings.py
sarif_manager/sarif/pdf_text.py
sarif_manager/sarif/slack_sarif.py
sarif_manager-0.4.2.dist-info/METADATA
sarif_manager-0.4.2.dist-info/WHEEL
sarif_manager-0.4.2.dist-info/entry_points.txt
sarif_manager-0.4.2.dist-info/top_level.txt
sarif_manager-0.4.2.dist-info/zip-safe
sarif_manager-0.4.2.dist-info/RECORD
