Metadata-Version: 2.2
Name: sarif_manager
Version: 0.4.2
Summary: A tool to manage SARIF files and integrations
Home-page: https://github.com/NimblerSecurity/sarif-manager
Author: Kinnaird McQuade
Author-email: kinnaird@nightvision.net
Keywords: sarif
Classifier: Programming Language :: Python :: 3
Classifier: Operating System :: OS Independent
Requires-Python: >=3.11
Requires-Dist: beautifulsoup4>=4.12.3
Requires-Dist: click
Requires-Dist: click-option-group
Requires-Dist: loguru
Requires-Dist: markdown>=3.5.0
Requires-Dist: requests>=2.31.0
Requires-Dist: python-dotenv==0.21.0
Requires-Dist: slack_sdk
Requires-Dist: reportlab>=4.0.0
Requires-Dist: markdown>=3.5.0
Requires-Dist: beautifulsoup4>=4.12.3
Requires-Dist: xhtml2pdf>=0.2.16
Provides-Extra: test
Requires-Dist: pytest>=7.0.0; extra == "test"
Requires-Dist: pytest-cov>=4.0.0; extra == "test"
Requires-Dist: pytest-mock>=3.10.0; extra == "test"
Dynamic: author
Dynamic: author-email
Dynamic: classifier
Dynamic: description
Dynamic: description-content-type
Dynamic: home-page
Dynamic: keywords
Dynamic: provides-extra
Dynamic: requires-dist
Dynamic: requires-python
Dynamic: summary
